archive_r.cpython-311-x86_64-linux-gnu.so
archive_r_python-0.1.14.data/data/.libs/libarchive_r_core.so
archive_r_python.libs/libacl-c64a7fa0.so.1.1.2302
archive_r_python.libs/libarchive-d09989d6.so.13.7.5
archive_r_python.libs/libarchive_r_core-16d872df.so
archive_r_python.libs/libattr-2d313358.so.1.1.2502
archive_r_python.libs/libb2-b7e27ba8.so.1.0.4
archive_r_python.libs/libbz2-a6e35ea0.so.1.0
archive_r_python.libs/liblz4-b4d8a4a4.so.1.10.0
archive_r_python.libs/liblzma-11fcb47c.so.5.6.2
archive_r_python.libs/libnettle-a4bbdfba.so.8.8
archive_r_python.libs/libomp-33594b64.so
archive_r_python.libs/libxml2-593e749b.so.2.13.4
archive_r_python.libs/libzstd-3bf64ae3.so.1.5.5
archive_r_python-0.1.14.dist-info/METADATA
archive_r_python-0.1.14.dist-info/WHEEL
archive_r_python-0.1.14.dist-info/top_level.txt
archive_r_python-0.1.14.dist-info/RECORD
archive_r_python-0.1.14.dist-info/licenses/LICENSE
archive_r_python-0.1.14.dist-info/licenses/NOTICE
archive_r_python-0.1.14.dist-info/licenses/LICENSES/acl-COPYING.LGPL
archive_r_python-0.1.14.dist-info/licenses/LICENSES/attr-COPYING.LGPL
archive_r_python-0.1.14.dist-info/licenses/LICENSES/bzip2-LICENSE
archive_r_python-0.1.14.dist-info/licenses/LICENSES/libarchive-COPYING
archive_r_python-0.1.14.dist-info/licenses/LICENSES/libb2-COPYING
archive_r_python-0.1.14.dist-info/licenses/LICENSES/libomp-LICENSE.TXT
archive_r_python-0.1.14.dist-info/licenses/LICENSES/libxml2-Copyright
archive_r_python-0.1.14.dist-info/licenses/LICENSES/lz4-LICENSE
archive_r_python-0.1.14.dist-info/licenses/LICENSES/nettle-COPYING.LESSERv3
archive_r_python-0.1.14.dist-info/licenses/LICENSES/nettle-COPYINGv2
archive_r_python-0.1.14.dist-info/licenses/LICENSES/xz-COPYING
archive_r_python-0.1.14.dist-info/licenses/LICENSES/xz-COPYING.0BSD
archive_r_python-0.1.14.dist-info/licenses/LICENSES/zstd-LICENSE
archive_r_python-0.1.14.dist-info/sboms/auditwheel.cdx.json
