Metadata-Version: 2.4
Name: archive_r_python
Version: 0.1.14
Summary: Python bindings for archive_r: libarchive-based streaming traversal for recursive nested archives (no temp files, no large in-memory buffers)
Home-page: https://github.com/Raizo-TCS/archive_r
Author: archive_r Team
Author-email: raizo.tcs@users.noreply.github.com
License: MIT
Project-URL: Source, https://github.com/Raizo-TCS/archive_r
Project-URL: Bug Tracker, https://github.com/Raizo-TCS/archive_r/issues
Project-URL: Documentation, https://github.com/Raizo-TCS/archive_r#readme
Keywords: archive libarchive traversal nested multi-volume
Classifier: Programming Language :: Python :: 3
Classifier: Programming Language :: Python :: 3.8
Classifier: Programming Language :: Python :: 3.9
Classifier: Programming Language :: Python :: 3.10
Classifier: Programming Language :: Python :: 3.11
Classifier: Programming Language :: Python :: 3.12
Classifier: Operating System :: POSIX :: Linux
Classifier: Operating System :: MacOS
Classifier: Operating System :: Microsoft :: Windows
Classifier: Development Status :: 4 - Beta
Classifier: Topic :: System :: Archiving
Classifier: Topic :: Software Development :: Libraries
Requires-Python: >=3.8
License-File: LICENSE
License-File: NOTICE
License-File: LICENSES/libarchive-COPYING
License-File: LICENSES/xz-COPYING
License-File: LICENSES/xz-COPYING.0BSD
License-File: LICENSES/nettle-COPYING.LESSERv3
License-File: LICENSES/nettle-COPYINGv2
License-File: LICENSES/attr-COPYING.LGPL
License-File: LICENSES/acl-COPYING.LGPL
License-File: LICENSES/libxml2-Copyright
License-File: LICENSES/lz4-LICENSE
License-File: LICENSES/zstd-LICENSE
License-File: LICENSES/libb2-COPYING
License-File: LICENSES/bzip2-LICENSE
License-File: LICENSES/libomp-LICENSE.TXT
Dynamic: description
Dynamic: description-content-type
Dynamic: license-file
